numeric_methods/__init__.py
numeric_methods/settings.py
numeric_methods/language/__init__.py
numeric_methods/language/properties.py
numeric_methods/language/variants.py
numeric_methods/language/docs/__init__.py
numeric_methods/language/docs/mathematics.py
numeric_methods/language/docs/one_variable.py
numeric_methods/language/docs/settings.py
numeric_methods/mathematics/__init__.py
numeric_methods/mathematics/compare.py
numeric_methods/mathematics/properties.py
numeric_methods/mathematics/types.py
numeric_methods/one_variable/__init__.py
numeric_methods/one_variable/false_method.py
numeric_methods/one_variable/half_method.py
numeric_methods/one_variable/iter_method.py
numeric_methods/one_variable/secant_method.py
numeric_methods/one_variable/tangent_method.py
test/__init__.py
test/test_mathematic.py
test/test_one_variable.py
test/test_settings.py
tests/__init__.py
tests/test_mathematic.py
tests/test_one_variable.py
tests/test_settings.py
numeric_methods-1.1.0.dist-info/LICENSE
numeric_methods-1.1.0.dist-info/METADATA
numeric_methods-1.1.0.dist-info/WHEEL
numeric_methods-1.1.0.dist-info/top_level.txt
numeric_methods-1.1.0.dist-info/RECORD
