Metadata-Version: 2.1
Name: numeric-methods
Version: 1.1.0
Summary: Numeric methods is a package of tools for analyze functions via numeric methods
Home-page: https://github.com/Helltraitor/numeric-methods
Author: Helltraitor
Author-email: helltraitor@hotmail.com
License: MIT
Project-URL: Bug Reports, https://github.com/Helltraitor/numeric-methods/issues
Project-URL: Source, https://github.com/Helltraitor/numeric-methods
Keywords: mathematics
Platform: UNKNOWN
Classifier: Development Status :: 5 - Production/Stable
Classifier: Intended Audience :: Science/Research
Classifier: Topic :: Scientific/Engineering :: Mathematics
Classifier: License :: OSI Approved :: MIT License
Classifier: Programming Language :: Python :: 3.10
Classifier: Programming Language :: Python :: 3 :: Only
Requires-Python: >=3.10, <4
License-File: LICENSE
